jupyterlab_commenting_service/__init__.py
jupyterlab_commenting_service/main.py
jupyterlab_commenting_service/service.py
jupyterlab_commenting_service-0.2.dist-info/LICENSE
jupyterlab_commenting_service-0.2.dist-info/METADATA
jupyterlab_commenting_service-0.2.dist-info/WHEEL
jupyterlab_commenting_service-0.2.dist-info/entry_points.txt
jupyterlab_commenting_service-0.2.dist-info/top_level.txt
jupyterlab_commenting_service-0.2.dist-info/RECORD
